{
  "project_info": {
    "project_number": "840502636880",
    "project_id": "bitcoin-c42b5",
    "storage_bucket": "bitcoin-c42b5.appspot.com"
  },
  "client": [
    {
      "client_info": {
        "mobilesdk_app_id": "1:840502636880:android:4f24317a340c89ac0e7c55",
        "android_client_info": {
          "package_name": "com.bitcoinbot.ea"
        }
      },
      "oauth_client": [
        {
          "client_id": "840502636880-9oc1ode22d4e0265jd3ed9uc8n6mul2d.apps.googleusercontent.com",
          "client_type": 3
        }
      ],
      "api_key": [
        {
          "current_key": "AIzaSyDSPIcAnjVjXXrHOlsRRAeSFdZmy_cpxVY"
        }
      ],
      "services": {
        "appinvite_service": {
          "other_platform_oauth_client": [
            {
              "client_id": "840502636880-9oc1ode22d4e0265jd3ed9uc8n6mul2d.apps.googleusercontent.com",
              "client_type": 3
            }
          ]
        }
      }
    }
  ],
  "configuration_version": "1"
}